fast_ml/__init__.py
fast_ml/eda.py
fast_ml/feature_engineering.py
fast_ml/feature_selection.py
fast_ml/missing_data_analysis.py
fast_ml/missing_data_imputation.py
fast_ml/model_development.py
fast_ml/model_evaluation.py
fast_ml/outlier_treatment.py
fast_ml/utilities.py
fast_ml/tools/EDA.py
fast_ml/tools/__init__.py
fast_ml/tools/fast_eda.py
fast_ml-3.68.dist-info/LICENSE
fast_ml-3.68.dist-info/METADATA
fast_ml-3.68.dist-info/WHEEL
fast_ml-3.68.dist-info/top_level.txt
fast_ml-3.68.dist-info/RECORD
