Metadata-Version: 2.1
Name: fast_ml
Version: 3.68
Summary: Package by the Data-Scientists for the Data Scientists ; with Scikit-learn type fit() transform() functionality
Home-page: https://github.com/samarth-agrawal-86/fast_ml
Author: Samarth Agrawal
Author-email: samarth.agrawal.86@gmail.com
License: UNKNOWN
Platform: UNKNOWN
Requires-Python: >=3.6
